g3t_etl/__init__.py
g3t_etl/cli.py
g3t_etl/factory.py
g3t_etl/loader.py
g3t_etl/submission_dictionary.py
g3t_etl/test_aced_etl.py
g3t_etl/transformer.py
g3t_etl/templates/Condition.yaml.jinja
g3t_etl/templates/Observation.yaml.jinja
g3t_etl/templates/Patient.yaml.jinja
g3t_etl/templates/Procedure.yaml.jinja
g3t_etl/templates/ResearchStudy.yaml.jinja
g3t_etl/templates/Specimen.yaml.jinja
g3t_etl/util/__init__.py
g3t_etl/util/local_fhir_db.py
tests/integration/__init__.py
tests/integration/conftest.py
tests/integration/test_extract.py
tests/integration/test_transform.py
tests/unit/__init__.py
tests/unit/conftest.py
tests/unit/test_cli.py
tests/unit/test_coding_conventions.py
tests/unit/test_local_db.py
tests/unit/test_spreadsheet_json_schema.py
tests/unit/templates/__init__.py
tests/unit/templates/conftest.py
tests/unit/templates/test_simple.py
tests/unit/templates/test_transformer.py
g3t_etl-0.0.1rc26.dist-info/METADATA
g3t_etl-0.0.1rc26.dist-info/WHEEL
g3t_etl-0.0.1rc26.dist-info/entry_points.txt
g3t_etl-0.0.1rc26.dist-info/top_level.txt
g3t_etl-0.0.1rc26.dist-info/RECORD
