Metadata-Version: 2.1
Name: g3t-etl
Version: 0.0.1rc26
Summary: Commons utilities
Home-page: https://github.com/ACED-IDP/g3t_etl.git
Author: Ellrott Lab
Project-URL: Bug Reports, https://github.com/ACED-IDP/gen3_util/issues
Project-URL: Source, https://github.com/ACED-IDP/gen3_util
Keywords: gen3 bioinformatics
Classifier: Development Status :: 3 - Alpha
Classifier: Intended Audience :: Developers
Classifier: Topic :: Software Development :: Build Tools
Classifier: License :: OSI Approved :: MIT License
Classifier: Programming Language :: Python :: 3.10
Requires-Python: >=3.9, <4
Requires-Dist: gen3-tracker >=0.0.4rc36
Requires-Dist: click
Requires-Dist: pandas
Requires-Dist: numpy
Requires-Dist: openpyxl
Requires-Dist: PyYAML
Requires-Dist: orjson
Requires-Dist: ndjson
Requires-Dist: inflection
Requires-Dist: jinja2
